Metadata-Version: 2.4
Name: llama-index-readers-couchdb
Version: 0.4.1
Summary: llama-index readers couchdb integration
Author-email: Your Name <you@example.com>
Maintainer: technosophy
License-Expression: MIT
License-File: LICENSE
Requires-Python: <4.0,>=3.9
Requires-Dist: couchdb3<2,>=1.2.1
Requires-Dist: llama-index-core<0.15,>=0.13.0
